SimpleJsonConfigParser/ConfigReader.py
SimpleJsonConfigParser/__init__.py
SimpleJsonConfigParser-1.0.4.dist-info/LICENSE
SimpleJsonConfigParser-1.0.4.dist-info/METADATA
SimpleJsonConfigParser-1.0.4.dist-info/WHEEL
SimpleJsonConfigParser-1.0.4.dist-info/top_level.txt
SimpleJsonConfigParser-1.0.4.dist-info/RECORD
