Metadata-Version: 2.1
Name: SimpleJsonConfigParser
Version: 1.0.4
Summary: Simple JSON Config Parser for Python.
Author: TPosty
Author-email: 
Keywords: python,configuration
Classifier: Development Status :: 1 - Planning
Classifier: Intended Audience :: Developers
Classifier: Programming Language :: Python :: 3
Classifier: Operating System :: Unix
Classifier: Operating System :: MacOS :: MacOS X
Classifier: Operating System :: Microsoft :: Windows
License-File: LICENSE
